odoo/addons/sale_order_product_recommendation/README.rst
odoo/addons/sale_order_product_recommendation/__init__.py
odoo/addons/sale_order_product_recommendation/__manifest__.py
odoo/addons/sale_order_product_recommendation/i18n/de.po
odoo/addons/sale_order_product_recommendation/i18n/es.po
odoo/addons/sale_order_product_recommendation/i18n/sale_order_product_recommendation.pot
odoo/addons/sale_order_product_recommendation/readme/CONTRIBUTORS.rst
odoo/addons/sale_order_product_recommendation/readme/DESCRIPTION.rst
odoo/addons/sale_order_product_recommendation/readme/USAGE.rst
odoo/addons/sale_order_product_recommendation/static/description/icon.png
odoo/addons/sale_order_product_recommendation/static/description/index.html
odoo/addons/sale_order_product_recommendation/tests/__init__.py
odoo/addons/sale_order_product_recommendation/tests/test_recommendation.py
odoo/addons/sale_order_product_recommendation/views/sale_order_view.xml
odoo/addons/sale_order_product_recommendation/wizards/__init__.py
odoo/addons/sale_order_product_recommendation/wizards/sale_order_recommendation.py
odoo/addons/sale_order_product_recommendation/wizards/sale_order_recommendation_view.xml
odoo11_addon_sale_order_product_recommendation-11.0.1.1.0.dist-info/METADATA
odoo11_addon_sale_order_product_recommendation-11.0.1.1.0.dist-info/WHEEL
odoo11_addon_sale_order_product_recommendation-11.0.1.1.0.dist-info/top_level.txt
odoo11_addon_sale_order_product_recommendation-11.0.1.1.0.dist-info/RECORD
